scripts/__init__.py
scripts/extract_svg_images.py
hgc_scripts-1.0.2.dist-info/METADATA
hgc_scripts-1.0.2.dist-info/WHEEL
hgc_scripts-1.0.2.dist-info/entry_points.txt
hgc_scripts-1.0.2.dist-info/top_level.txt
hgc_scripts-1.0.2.dist-info/RECORD
