Metadata-Version: 2.4
Name: hgc-scripts
Version: 1.0.2
Requires-Python: >=3.13
Requires-Dist: lxml>=5.2.0
Requires-Dist: httpx>=0.27.0
